weaklisp/__init__.py
weaklisp/__main__.py
weaklisp/formatter.py
weaklisp/parser.py
weaklisp-0.0.1.dist-info/DESCRIPTION.rst
weaklisp-0.0.1.dist-info/METADATA
weaklisp-0.0.1.dist-info/RECORD
weaklisp-0.0.1.dist-info/WHEEL
weaklisp-0.0.1.dist-info/metadata.json
weaklisp-0.0.1.dist-info/top_level.txt
