Metadata-Version: 2.0
Name: weaklisp
Version: 0.0.1
Summary: Analysis and documentation for very simple lisp.
Home-page: https://sourceforge.net/projects/weaklisp
Author: Yuri Teixeira
Author-email: yt@yuriteixeira.arq.br
License: AGPLv3+
Keywords: lisp analysis development
Platform: UNKNOWN
Classifier: Development Status :: 3 - Alpha
Classifier: Environment :: Console
Classifier: Intended Audience :: Developers
Classifier: Topic :: Software Development :: Quality Assurance
Classifier: License :: OSI Approved :: GNU Affero General Public License v3 or later (AGPLv3+)
Classifier: Programming Language :: Python :: 3
Requires-Dist: pyparsing
